sphinx_view/__init__.py
sphinx_view/builders.py
sphinx_view/views.py
sphinx_view/templates/sphinx_view/page.html
django_sphinx_view-23.1a7.dist-info/WHEEL
django_sphinx_view-23.1a7.dist-info/METADATA
django_sphinx_view-23.1a7.dist-info/RECORD
