Metadata-Version: 2.1
Name: django-sphinx-view
Version: 23.1a7
Summary: Serve your Sphinx docs with Django.
Home-page: https://noumenal.es/django-sphinx-view/
Author: Carlton Gibson
Author-email: carlton.gibson@noumenal.es
Project-URL: GitHub, https://github.com/carltongibson/django-sphinx-view
